{
  "fill" : {
    "solid" : "extended-gray:1.00000,1.00000"
  },
  "groups" : [
    {
      "layers" : [
        {
          "glass" : true,
          "image-name" : "lower-left.svg",
          "name" : "Lower left"
        },
        {
          "glass" : true,
          "image-name" : "right.svg",
          "name" : "Right"
        },
        {
          "glass" : true,
          "image-name" : "top.svg",
          "name" : "Top"
        }
      ],
      "lighting" : "combined",
      "shadow" : {
        "kind" : "layer-color",
        "opacity" : 0.35
      },
      "translucency" : {
        "enabled" : true,
        "value" : 0.08
      }
    },
    {
      "layers" : [
        {
          "glass" : false,
          "image-name" : "center.svg",
          "name" : "Center"
        }
      ],
      "shadow" : {
        "kind" : "neutral",
        "opacity" : 0.35
      },
      "translucency" : {
        "enabled" : false,
        "value" : 0
      }
    }
  ],
  "supported-platforms" : {
    "squares" : "shared"
  }
}
